my_cool_package/__init__.py
my_cool_package/upgrader.py
mycoolpackage_bdd4329-0.1.7.dist-info/METADATA
mycoolpackage_bdd4329-0.1.7.dist-info/WHEEL
mycoolpackage_bdd4329-0.1.7.dist-info/RECORD
