Metadata-Version: 2.1
Name: mycoolpackage-bdd4329
Version: 0.1.7
Summary: A useful description
Author: Shannon Byrnes
Author-email: sbyrnes@internet2.edu
Requires-Python: >=3.9,<4.0
Classifier: Programming Language :: Python :: 3
Classifier: Programming Language :: Python :: 3.9
Classifier: Programming Language :: Python :: 3.10
Classifier: Programming Language :: Python :: 3.11
